deutschland/marktstammdaten/__init__.py
deutschland/marktstammdaten/api/__init__.py
deutschland/marktstammdaten/api/daten_api.py
deutschland/marktstammdaten/api/filter_api.py
deutschland/marktstammdaten/api_client.py
deutschland/marktstammdaten/apis/__init__.py
deutschland/marktstammdaten/configuration.py
deutschland/marktstammdaten/exceptions.py
deutschland/marktstammdaten/model/__init__.py
deutschland/marktstammdaten/model/einheit_einheit_json_get_erweiterte_oeffentliche_einheit_stromerzeugung_get200_response.py
deutschland/marktstammdaten/model/entry.py
deutschland/marktstammdaten/model/filter.py
deutschland/marktstammdaten/model/filter_list_object_inner.py
deutschland/marktstammdaten/model_utils.py
deutschland/marktstammdaten/models/__init__.py
deutschland/marktstammdaten/rest.py
de_marktstammdaten-0.1.0.dist-info/WHEEL
de_marktstammdaten-0.1.0.dist-info/METADATA
de_marktstammdaten-0.1.0.dist-info/RECORD
